<?xml version="1.0" encoding="utf-8"?>
<Window>
	<Form Height="577" Id="D1504010010F" Left="8" OnLoadCompleted="D1504010010F_OnLoadCompleted" PidAttrib="7" Title="위험작업&#32;GIS데이터&#32;수정의뢰메인_D1504010010F" Top="8" Ver="1.0" Width="1005" WorkArea="false">
		<Shape BKColor="#6cbae1" Bottom="102" Height="13" Id="Shape0" Left="5" LineWidth="0" Right="1000" TabOrder="2" Top="89" Type="Rectangle" Width="995"></Shape>
		<Grid AutoEnter="TRUE" AutoFit="TRUE" BindDataset="ds_suppress" BkColor2="user3" BoldHead="FALSE" Border="Flat" Bottom="249" ColSizing="TRUE" Enable="true" EndLineColor="default" HeadBorder="Flat" HeadHeight="20" Height="157" Id="Grid0" InputPanel="FALSE" Left="5" LineColor="default" LineType="ExVERT" MinWidth="100" MultiSelect="TRUE" Right="1000" ScrollCell="true" SelColor="BACKGROUND" Style="grid" TabOrder="1" TabStop="true" Top="92" UseDBuff="true" UsePopupMenu="true" UseSelColor="true" Visible="true" VLineColor="default" WheelScrollRow="1" Width="995">
			<contents>
				<format id="Default">
					<columns>
						<col fix="left" width="50"/>
						<col width="100"/>
						<col width="120"/>
						<col width="150"/>
						<col width="80"/>
						<col width="80"/>
					</columns>
					<head>
						<cell bkcolor="user11" col="0" display="normal" text="NO"/>
						<cell bkcolor="user11" col="1" display="text" text="위험작업코드"/>
						<cell bkcolor="user11" col="2" display="text" text="위험작업명"/>
						<cell bkcolor="user11" col="3" display="text" text="작업위치"/>
						<cell bkcolor="user11" col="4" display="text" text="작업요청일"/>
						<cell bkcolor="user11" col="5" display="text" text="작업구분"/>
					</head>
					<body>
						<cell col="0" display="normal" expandsize="18" wordwrap="word"/>
						<cell col="1" display="text" expandsize="18" wordwrap="word"/>
						<cell col="2" display="text" expandsize="18" wordwrap="word"/>
						<cell col="3" display="text" expandsize="18" wordwrap="word"/>
						<cell col="4" display="text" expandsize="18" wordwrap="word"/>
						<cell col="5" display="text"/>
					</body>
				</format>
			</contents>
		</Grid>
		<Div DisableBKColor="white" Height="30" Id="Div0" Left="5" OnLoadCompleted="ComButton_OnLoadCompleted" OnTimer="ComButton_OnTimer" TabOrder="3" Text="Div0" Url="globals::ComHead.xml" Visible="FALSE" Width="995">
			<Contents></Contents>
		</Div>
		<Tab Border="Flat" FixedImage="FALSE" Height="326" Id="Tab0" Left="5" Style="tab" TabOrder="4" Top="251" Width="995">
			<Contents>
				<TabPage Height="296" Id="tab16" ImageID="tab" Left="2" scroll="true" Style="tab" TabOrder="60" Text="GIS&#32;DATA수정의뢰" Top="28" Url="D10::D1504010010F_T01.xml" Width="991"></TabPage>
				<TabPage Height="296" Id="tab4" ImageID="tab" Left="2" Style="tab" TabOrder="13" Text="중폐지작업결과서" Top="28" Url="D10::D1103010010F_T02.xml" Width="991"></TabPage>
				<TabPage Height="296" Id="tab5" ImageID="tab" Left="2" scroll="true" TabOrder="13" Text="업체평가" Top="28" Url="D10::D1103010010F_T03.xml" Width="991"></TabPage>
				<TabPage Height="296" Id="Tab0" ImageID="tab" Left="2" Style="tab" TabOrder="11" Text="현장입회확인" Top="28" Url="D10::D1103010010F_T04.xml" Width="991"></TabPage>
			</Contents>
		</Tab>
		<Shape BKColor="user6" Bottom="69" Height="39" Id="Shape1" Left="5" LineColor="user7" Right="1000" RoundHeight="3" RoundUnit="Pixel" RoundWidth="3" TabOrder="8" Top="30" Type="RoundRect" Width="995"></Shape>
		<Shape BKColor="user8" Bottom="64" Height="29" Id="Shape2" Left="10" LineWidth="0" Right="995" RoundHeight="3" RoundUnit="Pixel" RoundWidth="3" TabOrder="9" Top="35" Type="Rectangle" Width="985"></Shape>
		<Image Align="Left" Height="6" Id="Image5" ImageID="blt" Left="13" LeftMargin="12" Style="blt_search_1" TabOrder="5" Text="지사" Top="46" Width="59"></Image>
		<Image Align="Left" Height="6" Id="Image3" ImageID="blt" Left="179" LeftMargin="12" Style="blt_search_1" TabOrder="6" Text="구" Top="46" Width="59"></Image>
		<Image Align="Left" Height="6" Id="Image4" ImageID="blt" Left="690" LeftMargin="12" Style="blt_search_1" TabOrder="7" Text="요청일자" Top="46" Width="59"></Image>
		<Combo Border="Flat" Height="18" Id="Combo0" Left="53" Style="combo_indis" TabOrder="10" Top="39" Width="114"></Combo>
		<Combo Border="Flat" Height="18" Id="Combo1" Left="206" Style="combo_indis" TabOrder="11" Top="39" Width="114"></Combo>
		<Calendar Border="Flat" DayFont="Default,-1" HeaderFont="Default,-1" Height="18" Id="Calendar1" Left="755" SaturdayTextColor="blue" SelectedDayFont="Default,-1" Style="calendar_indis" SundayTextColor="red" TabOrder="12" Top="40" WeeksFont="Default,-1" Width="88"></Calendar>
		<Static Height="13" Id="Static10" Left="844" Style="static" TabOrder="13" Text="~" Top="43" Width="10"></Static>
		<Calendar Border="Flat" DayFont="Default,-1" HeaderFont="Default,-1" Height="18" Id="Calendar2" Left="854" SaturdayTextColor="blue" SelectedDayFont="Default,-1" Style="calendar_indis" SundayTextColor="red" TabOrder="14" Top="40" WeeksFont="Default,-1" Width="88"></Calendar>
		<Image Align="Left" Height="6" Id="Image8" ImageID="blt" Left="329" LeftMargin="12" Style="blt_search_1" TabOrder="15" Text="시공사" Top="46" Width="59"></Image>
		<Combo Border="Flat" Height="18" Id="Combo8" Left="381" Style="combo_indis" TabOrder="16" Top="39" Width="114"></Combo>
		<Combo Border="Flat" Height="18" Id="Combo9" Left="567" Style="combo_indis" TabOrder="18" Top="39" Width="114"></Combo>
		<Image Align="Left" Height="6" Id="Image10" ImageID="blt" Left="504" LeftMargin="12" Style="blt_search_1" TabOrder="17" Text="작업구분" Top="46" Width="59"></Image>
		<Image Align="Left" Height="9" Id="Image9" ImageID="blt_8" Left="5" LeftMargin="12" OnClick="Image13_OnClick" Style="text_title" TabOrder="19" Text="위험작업조회" Top="75" Width="127"></Image>
	</Form>
	<Script><![CDATA[#include "JS::COMMONA10001.js";

function D1504010010F_OnLoadCompleted(obj)
{
	gfn_LoadForm(obj);
}]]></Script>
</Window>